morbin/__init__.py
morbin/morbin.py
morbin/py.typed
morbin/template.py
morbin-1.0.1.dist-info/METADATA
morbin-1.0.1.dist-info/WHEEL
morbin-1.0.1.dist-info/entry_points.txt
morbin-1.0.1.dist-info/licenses/LICENSE.txt
morbin-1.0.1.dist-info/RECORD
