Metadata-Version: 2.1
Name: morbin
Version: 1.0.1
Summary: Base class for creating modules that are bindings for command line tools.
Project-URL: Homepage, https://github.com/matt-manes/morbin
Project-URL: Documentation, https://github.com/matt-manes/morbin/tree/main/docs
Project-URL: Source code, https://github.com/matt-manes/morbin/tree/main/src/morbin
Author-email: Matt Manes <mattmanes@pm.me>
License-File: LICENSE.txt
Keywords: binding,bindings,cli,morbin,morbius,morph,terminal
Classifier: License :: OSI Approved :: MIT License
Classifier: Operating System :: OS Independent
Classifier: Programming Language :: Python :: 3
Requires-Python: <3.12,>=3.10
Requires-Dist: pathier
Requires-Dist: typing-extensions
